<annotation>
	<folder>螺帽</folder>
	<filename>螺帽_180807_0041.jpg</filename>
	<path>D:\data_op\螺帽\螺帽_180807_0041.jpg</path>
	<source>
		<database>Unknown</database>
	</source>
	<size>
		<width>1108</width>
		<height>1478</height>
		<depth>3</depth>
	</size>
	<segmented>0</segmented>
	<object>
		<name>nut</name>
		<pose>Unspecified</pose>
		<truncated>0</truncated>
		<difficult>0</difficult>
		<bndbox>
			<xmin>817</xmin>
			<ymin>936</ymin>
			<xmax>977</xmax>
			<ymax>1085</ymax>
		</bndbox>
	</object>
	<object>
		<name>nut</name>
		<pose>Unspecified</pose>
		<truncated>1</truncated>
		<difficult>0</difficult>
		<bndbox>
			<xmin>817</xmin>
			<ymin>1349</ymin>
			<xmax>981</xmax>
			<ymax>1478</ymax>
		</bndbox>
	</object>
</annotation>
